satchless/__init__.py
satchless/cart/__init__.py
satchless/cart/test_cart.py
satchless/item/__init__.py
satchless/item/test_item.py
satchless/process/__init__.py
satchless/process/test_process.py
satchless-1.3.dist-info/LICENSE
satchless-1.3.dist-info/METADATA
satchless-1.3.dist-info/WHEEL
satchless-1.3.dist-info/top_level.txt
satchless-1.3.dist-info/zip-safe
satchless-1.3.dist-info/RECORD
